crecombio/__init__.py
crecombio/crecombio.py
crecombio-0.1.2.dist-info/licenses/LICENSE
examples/two_sequences.py
images/flp_frt_plot.py
tests/test_crecombio.py
crecombio-0.1.2.dist-info/METADATA
crecombio-0.1.2.dist-info/WHEEL
crecombio-0.1.2.dist-info/top_level.txt
crecombio-0.1.2.dist-info/RECORD
