Metadata-Version: 2.4
Name: crecombio
Version: 0.1.2
Summary: Site-specific DNA recombination simulator
Author: Peter Vegh
License-Expression: MIT
Project-URL: Homepage, https://github.com/Edinburgh-Genome-Foundry/crecombio/
Keywords: biology
License-File: LICENSE
Requires-Dist: biopython
Dynamic: license-file
